Workbook

Sheet Parametri
A1: Pianificatore obiettivi — Parametri globali
A2: Modifica le celle in BLU. Rendimenti per profilo: assunzioni editabili, nominali e netti (note 6-7).
A4: PARAMETRI GLOBALI
A5: Capacità di risparmio mensile | B5: 1200 | C5: €/mese (entrate − spese)
A6: Inflazione attesa | B6: 0.02 | C6: target BCE 2%
A7: Finestra di de-risking (anni) | B7: 7 | C7: glide path: negli ultimi anni i terminanti scendono a 0% azionario
A8: RENDIMENTI PER PROFILO (nominali, netti di costi e imposte, editabili)
A9: Profilo | B9: Rendimento atteso | C9: Volatilità attesa | D9: % Azionario | E9: Orizzonte tipico
A10: Preservazione | B10: 0.015 | C10: 0.015 | D10: 0 | E10: < 2 anni
A11: Conservativo | B11: 0.025 | C11: 0.045 | D11: 0.1 | E11: 2-4 anni
A12: Moderato | B12: 0.04 | C12: 0.085 | D12: 0.4 | E12: 4-7 anni
A13: Crescita | B13: 0.055 | C13: 0.13 | D13: 0.65 | E13: 7-12 anni
A14: Crescita massima | B14: 0.065 | C14: 0.165 | D14: 0.9 | E14: > 12 anni
A15: Azionario totale | B15: 0.069 | C15: 0.18 | D15: 1
A17: NOTE:
A18: 1. Rendimenti, volatilità e % azionario sono ipotesi/esempi editabili. La % azionario è il punto medio rappresentativo della fascia del profilo.
A19: 2. L'orizzonte di un obiettivo guida la scelta del profilo (più corto = più conservativo). Vedi orizzonte-allocazione.md.
A20: 3. Il fondo di emergenza va in 'Preservazione' (liquidità): è l'obiettivo 0, prima di ogni altro.
A21: 4. La volatilità alimenta il Monte Carlo (montecarlo-obiettivi.py); la % azionario alimenta l'allocazione complessiva (foglio Riepilogo).
A22: 5. Non è consulenza di investimento: i profili sono esempi didattici, la scelta è dell'utente.
A23: 6. Netti di costi e imposte: netto ≈ (lordo − costi) × (1 − 26%), come se tassati ogni anno (prudente). L'asset location riparte dal lordo.
A24: 7. Media aritmetica annua attesa: la crescita composta mediana è ≈ rendimento − volatilità²/2 (da dati annualizzati, es. DMS: aggiungere volatilità²/2).
A25: 8. Finestra (B7): i terminanti de-riskano negli ultimi anni fino a 0% azionario; il versamento (Obiettivi, colonne I, O, P) ne tiene conto.

Sheet Obiettivi
A1: Pianificatore obiettivi — Tabella obiettivi
A2: Compila una riga per obiettivo (celle BLU). Profilo, Priorità e Tipo hanno un menu a tendina. Tipo: 'terminante' = si spende a scadenza (casa, università) e de-riska negli ultimi anni (colonne O-P, finestra in Parametri!B7); 'permanente' = cuscinetto/riserva che resta (fondo emergenza). Usato dal versamento e dal glide path.
A4: Obiettivo | B4: Importo target (€ oggi) | C4: Orizzonte (anni) | D4: Profilo | E4: Rendimento atteso | F4: Già accantonato | G4: Priorità | H4: Target nominale (€) | I4: Versamento mensile (€) | J4: % capacità | K4: % Azionario | L4: Capitale azionario (€) | M4: Versam. azionario (€) | N4: Tipo | O4: Anni di de-risking | P4: Rendimento in de-risking
A5: Fondo di emergenza | B5: 12000 | C5: 2 | D5: Preservazione | E5: =IF(D5="","",IFERROR(VLOOKUP(D5,Parametri!$A$10:$E$15,2,FALSE()),"?")) -> 0.015 | F5: 0 | G5: essenziale | H5: =IF(AND(ISNUMBER(B5),ISNUMBER(C5)),B5*(1+Parametri!$B$6)^C5,"") -> 12484.8 | I5: =IF(AND(ISNUMBER(B5),ISNUMBER(C5),ISNUMBER(E5),ISNUMBER(O5),ISNUMBER(P5)),MAX(0,(H5-IF(ISNUMBER(F5),F5,0)*(1+E5)^(C5-O5)*(1+P5)^O5)/(IF(E5=0,12*(C5-O5),((1+E5)^(C5-O5)-1)/((1+E5)^(1/12)-1))*(1+P5)^O5+IF(P5=0,12*O5,((1+P5)^O5-1)/((1+P5)^(1/12)-1)))),"") -> 512.81144 | J5: =IF(ISNUMBER(I5),I5/Parametri!$B$5,"") -> 0.42734287 | K5: =IF(D5="","",IFERROR(VLOOKUP(D5,Parametri!$A$10:$E$15,4,FALSE()),"")) -> 0 | L5: =IF(AND(ISNUMBER(F5),ISNUMBER(K5)),F5*K5,"") -> 0 | M5: =IF(AND(ISNUMBER(I5),ISNUMBER(K5)),I5*K5,"") -> 0 | N5: permanente | O5: =IF(NOT(ISNUMBER(C5)),"",IF(OR(N5="permanente",NOT(ISNUMBER(K5)),K5<=MIN(Parametri!$D$10:$D$15)),0,MAX(0,MIN(Parametri!$B$7,C5)-1))) -> 0 | P5: =IF(OR(NOT(ISNUMBER(E5)),NOT(ISNUMBER(O5))),"",IF(O5=0,E5,(E5+INDEX(Parametri!$B$10:$B$15,MATCH(MIN(Parametri!$D$10:$D$15),Parametri!$D$10:$D$15,0)))/2)) -> 0.015
A6: Anticipo casa | B6: 40000 | C6: 6 | D6: Moderato | E6: =IF(D6="","",IFERROR(VLOOKUP(D6,Parametri!$A$10:$E$15,2,FALSE()),"?")) -> 0.04 | F6: 5000 | G6: importante | H6: =IF(AND(ISNUMBER(B6),ISNUMBER(C6)),B6*(1+Parametri!$B$6)^C6,"") -> 45046.497 | I6: =IF(AND(ISNUMBER(B6),ISNUMBER(C6),ISNUMBER(E6),ISNUMBER(O6),ISNUMBER(P6)),MAX(0,(H6-IF(ISNUMBER(F6),F6,0)*(1+E6)^(C6-O6)*(1+P6)^O6)/(IF(E6=0,12*(C6-O6),((1+E6)^(C6-O6)-1)/((1+E6)^(1/12)-1))*(1+P6)^O6+IF(P6=0,12*O6,((1+P6)^O6-1)/((1+P6)^(1/12)-1)))),"") -> 500.01023 | J6: =IF(ISNUMBER(I6),I6/Parametri!$B$5,"") -> 0.4166752 | K6: =IF(D6="","",IFERROR(VLOOKUP(D6,Parametri!$A$10:$E$15,4,FALSE()),"")) -> 0.4 | L6: =IF(AND(ISNUMBER(F6),ISNUMBER(K6)),F6*K6,"") -> 2000 | M6: =IF(AND(ISNUMBER(I6),ISNUMBER(K6)),I6*K6,"") -> 200.00409 | N6: terminante | O6: =IF(NOT(ISNUMBER(C6)),"",IF(OR(N6="permanente",NOT(ISNUMBER(K6)),K6<=MIN(Parametri!$D$10:$D$15)),0,MAX(0,MIN(Parametri!$B$7,C6)-1))) -> 5 | P6: =IF(OR(NOT(ISNUMBER(E6)),NOT(ISNUMBER(O6))),"",IF(O6=0,E6,(E6+INDEX(Parametri!$B$10:$B$15,MATCH(MIN(Parametri!$D$10:$D$15),Parametri!$D$10:$D$15,0)))/2)) -> 0.0275
A7: Lungo termine / libertà | B7: 100000 | C7: 20 | D7: Crescita | E7: =IF(D7="","",IFERROR(VLOOKUP(D7,Parametri!$A$10:$E$15,2,FALSE()),"?")) -> 0.055 | F7: 0 | G7: desiderabile | H7: =IF(AND(ISNUMBER(B7),ISNUMBER(C7)),B7*(1+Parametri!$B$6)^C7,"") -> 148594.74 | I7: =IF(AND(ISNUMBER(B7),ISNUMBER(C7),ISNUMBER(E7),ISNUMBER(O7),ISNUMBER(P7)),MAX(0,(H7-IF(ISNUMBER(F7),F7,0)*(1+E7)^(C7-O7)*(1+P7)^O7)/(IF(E7=0,12*(C7-O7),((1+E7)^(C7-O7)-1)/((1+E7)^(1/12)-1))*(1+P7)^O7+IF(P7=0,12*O7,((1+P7)^O7-1)/((1+P7)^(1/12)-1)))),"") -> 384.29862 | J7: =IF(ISNUMBER(I7),I7/Parametri!$B$5,"") -> 0.32024885 | K7: =IF(D7="","",IFERROR(VLOOKUP(D7,Parametri!$A$10:$E$15,4,FALSE()),"")) -> 0.65 | L7: =IF(AND(ISNUMBER(F7),ISNUMBER(K7)),F7*K7,"") -> 0 | M7: =IF(AND(ISNUMBER(I7),ISNUMBER(K7)),I7*K7,"") -> 249.79411 | N7: terminante | O7: =IF(NOT(ISNUMBER(C7)),"",IF(OR(N7="permanente",NOT(ISNUMBER(K7)),K7<=MIN(Parametri!$D$10:$D$15)),0,MAX(0,MIN(Parametri!$B$7,C7)-1))) -> 6 | P7: =IF(OR(NOT(ISNUMBER(E7)),NOT(ISNUMBER(O7))),"",IF(O7=0,E7,(E7+INDEX(Parametri!$B$10:$B$15,MATCH(MIN(Parametri!$D$10:$D$15),Parametri!$D$10:$D$15,0)))/2)) -> 0.035
E8: =IF(D8="","",IFERROR(VLOOKUP(D8,Parametri!$A$10:$E$15,2,FALSE()),"?")) | H8: =IF(AND(ISNUMBER(B8),ISNUMBER(C8)),B8*(1+Parametri!$B$6)^C8,"") | I8: =IF(AND(ISNUMBER(B8),ISNUMBER(C8),ISNUMBER(E8),ISNUMBER(O8),ISNUMBER(P8)),MAX(0,(H8-IF(ISNUMBER(F8),F8,0)*(1+E8)^(C8-O8)*(1+P8)^O8)/(IF(E8=0,12*(C8-O8),((1+E8)^(C8-O8)-1)/((1+E8)^(1/12)-1))*(1+P8)^O8+IF(P8=0,12*O8,((1+P8)^O8-1)/((1+P8)^(1/12)-1)))),"") | J8: =IF(ISNUMBER(I8),I8/Parametri!$B$5,"") | K8: =IF(D8="","",IFERROR(VLOOKUP(D8,Parametri!$A$10:$E$15,4,FALSE()),"")) | L8: =IF(AND(ISNUMBER(F8),ISNUMBER(K8)),F8*K8,"") | M8: =IF(AND(ISNUMBER(I8),ISNUMBER(K8)),I8*K8,"") | O8: =IF(NOT(ISNUMBER(C8)),"",IF(OR(N8="permanente",NOT(ISNUMBER(K8)),K8<=MIN(Parametri!$D$10:$D$15)),0,MAX(0,MIN(Parametri!$B$7,C8)-1))) | P8: =IF(OR(NOT(ISNUMBER(E8)),NOT(ISNUMBER(O8))),"",IF(O8=0,E8,(E8+INDEX(Parametri!$B$10:$B$15,MATCH(MIN(Parametri!$D$10:$D$15),Parametri!$D$10:$D$15,0)))/2))
E9: =IF(D9="","",IFERROR(VLOOKUP(D9,Parametri!$A$10:$E$15,2,FALSE()),"?")) | H9: =IF(AND(ISNUMBER(B9),ISNUMBER(C9)),B9*(1+Parametri!$B$6)^C9,"") | I9: =IF(AND(ISNUMBER(B9),ISNUMBER(C9),ISNUMBER(E9),ISNUMBER(O9),ISNUMBER(P9)),MAX(0,(H9-IF(ISNUMBER(F9),F9,0)*(1+E9)^(C9-O9)*(1+P9)^O9)/(IF(E9=0,12*(C9-O9),((1+E9)^(C9-O9)-1)/((1+E9)^(1/12)-1))*(1+P9)^O9+IF(P9=0,12*O9,((1+P9)^O9-1)/((1+P9)^(1/12)-1)))),"") | J9: =IF(ISNUMBER(I9),I9/Parametri!$B$5,"") | K9: =IF(D9="","",IFERROR(VLOOKUP(D9,Parametri!$A$10:$E$15,4,FALSE()),"")) | L9: =IF(AND(ISNUMBER(F9),ISNUMBER(K9)),F9*K9,"") | M9: =IF(AND(ISNUMBER(I9),ISNUMBER(K9)),I9*K9,"") | O9: =IF(NOT(ISNUMBER(C9)),"",IF(OR(N9="permanente",NOT(ISNUMBER(K9)),K9<=MIN(Parametri!$D$10:$D$15)),0,MAX(0,MIN(Parametri!$B$7,C9)-1))) | P9: =IF(OR(NOT(ISNUMBER(E9)),NOT(ISNUMBER(O9))),"",IF(O9=0,E9,(E9+INDEX(Parametri!$B$10:$B$15,MATCH(MIN(Parametri!$D$10:$D$15),Parametri!$D$10:$D$15,0)))/2))
E10: =IF(D10="","",IFERROR(VLOOKUP(D10,Parametri!$A$10:$E$15,2,FALSE()),"?")) | H10: =IF(AND(ISNUMBER(B10),ISNUMBER(C10)),B10*(1+Parametri!$B$6)^C10,"") | I10: =IF(AND(ISNUMBER(B10),ISNUMBER(C10),ISNUMBER(E10),ISNUMBER(O10),ISNUMBER(P10)),MAX(0,(H10-IF(ISNUMBER(F10),F10,0)*(1+E10)^(C10-O10)*(1+P10)^O10)/(IF(E10=0,12*(C10-O10),((1+E10)^(C10-O10)-1)/((1+E10)^(1/12)-1))*(1+P10)^O10+IF(P10=0,12*O10,((1+P10)^O10-1)/((1+P10)^(1/12)-1)))),"") | J10: =IF(ISNUMBER(I10),I10/Parametri!$B$5,"") | K10: =IF(D10="","",IFERROR(VLOOKUP(D10,Parametri!$A$10:$E$15,4,FALSE()),"")) | L10: =IF(AND(ISNUMBER(F10),ISNUMBER(K10)),F10*K10,"") | M10: =IF(AND(ISNUMBER(I10),ISNUMBER(K10)),I10*K10,"") | O10: =IF(NOT(ISNUMBER(C10)),"",IF(OR(N10="permanente",NOT(ISNUMBER(K10)),K10<=MIN(Parametri!$D$10:$D$15)),0,MAX(0,MIN(Parametri!$B$7,C10)-1))) | P10: =IF(OR(NOT(ISNUMBER(E10)),NOT(ISNUMBER(O10))),"",IF(O10=0,E10,(E10+INDEX(Parametri!$B$10:$B$15,MATCH(MIN(Parametri!$D$10:$D$15),Parametri!$D$10:$D$15,0)))/2))
E11: =IF(D11="","",IFERROR(VLOOKUP(D11,Parametri!$A$10:$E$15,2,FALSE()),"?")) | H11: =IF(AND(ISNUMBER(B11),ISNUMBER(C11)),B11*(1+Parametri!$B$6)^C11,"") | I11: =IF(AND(ISNUMBER(B11),ISNUMBER(C11),ISNUMBER(E11),ISNUMBER(O11),ISNUMBER(P11)),MAX(0,(H11-IF(ISNUMBER(F11),F11,0)*(1+E11)^(C11-O11)*(1+P11)^O11)/(IF(E11=0,12*(C11-O11),((1+E11)^(C11-O11)-1)/((1+E11)^(1/12)-1))*(1+P11)^O11+IF(P11=0,12*O11,((1+P11)^O11-1)/((1+P11)^(1/12)-1)))),"") | J11: =IF(ISNUMBER(I11),I11/Parametri!$B$5,"") | K11: =IF(D11="","",IFERROR(VLOOKUP(D11,Parametri!$A$10:$E$15,4,FALSE()),"")) | L11: =IF(AND(ISNUMBER(F11),ISNUMBER(K11)),F11*K11,"") | M11: =IF(AND(ISNUMBER(I11),ISNUMBER(K11)),I11*K11,"") | O11: =IF(NOT(ISNUMBER(C11)),"",IF(OR(N11="permanente",NOT(ISNUMBER(K11)),K11<=MIN(Parametri!$D$10:$D$15)),0,MAX(0,MIN(Parametri!$B$7,C11)-1))) | P11: =IF(OR(NOT(ISNUMBER(E11)),NOT(ISNUMBER(O11))),"",IF(O11=0,E11,(E11+INDEX(Parametri!$B$10:$B$15,MATCH(MIN(Parametri!$D$10:$D$15),Parametri!$D$10:$D$15,0)))/2))
E12: =IF(D12="","",IFERROR(VLOOKUP(D12,Parametri!$A$10:$E$15,2,FALSE()),"?")) | H12: =IF(AND(ISNUMBER(B12),ISNUMBER(C12)),B12*(1+Parametri!$B$6)^C12,"") | I12: =IF(AND(ISNUMBER(B12),ISNUMBER(C12),ISNUMBER(E12),ISNUMBER(O12),ISNUMBER(P12)),MAX(0,(H12-IF(ISNUMBER(F12),F12,0)*(1+E12)^(C12-O12)*(1+P12)^O12)/(IF(E12=0,12*(C12-O12),((1+E12)^(C12-O12)-1)/((1+E12)^(1/12)-1))*(1+P12)^O12+IF(P12=0,12*O12,((1+P12)^O12-1)/((1+P12)^(1/12)-1)))),"") | J12: =IF(ISNUMBER(I12),I12/Parametri!$B$5,"") | K12: =IF(D12="","",IFERROR(VLOOKUP(D12,Parametri!$A$10:$E$15,4,FALSE()),"")) | L12: =IF(AND(ISNUMBER(F12),ISNUMBER(K12)),F12*K12,"") | M12: =IF(AND(ISNUMBER(I12),ISNUMBER(K12)),I12*K12,"") | O12: =IF(NOT(ISNUMBER(C12)),"",IF(OR(N12="permanente",NOT(ISNUMBER(K12)),K12<=MIN(Parametri!$D$10:$D$15)),0,MAX(0,MIN(Parametri!$B$7,C12)-1))) | P12: =IF(OR(NOT(ISNUMBER(E12)),NOT(ISNUMBER(O12))),"",IF(O12=0,E12,(E12+INDEX(Parametri!$B$10:$B$15,MATCH(MIN(Parametri!$D$10:$D$15),Parametri!$D$10:$D$15,0)))/2))
E13: =IF(D13="","",IFERROR(VLOOKUP(D13,Parametri!$A$10:$E$15,2,FALSE()),"?")) | H13: =IF(AND(ISNUMBER(B13),ISNUMBER(C13)),B13*(1+Parametri!$B$6)^C13,"") | I13: =IF(AND(ISNUMBER(B13),ISNUMBER(C13),ISNUMBER(E13),ISNUMBER(O13),ISNUMBER(P13)),MAX(0,(H13-IF(ISNUMBER(F13),F13,0)*(1+E13)^(C13-O13)*(1+P13)^O13)/(IF(E13=0,12*(C13-O13),((1+E13)^(C13-O13)-1)/((1+E13)^(1/12)-1))*(1+P13)^O13+IF(P13=0,12*O13,((1+P13)^O13-1)/((1+P13)^(1/12)-1)))),"") | J13: =IF(ISNUMBER(I13),I13/Parametri!$B$5,"") | K13: =IF(D13="","",IFERROR(VLOOKUP(D13,Parametri!$A$10:$E$15,4,FALSE()),"")) | L13: =IF(AND(ISNUMBER(F13),ISNUMBER(K13)),F13*K13,"") | M13: =IF(AND(ISNUMBER(I13),ISNUMBER(K13)),I13*K13,"") | O13: =IF(NOT(ISNUMBER(C13)),"",IF(OR(N13="permanente",NOT(ISNUMBER(K13)),K13<=MIN(Parametri!$D$10:$D$15)),0,MAX(0,MIN(Parametri!$B$7,C13)-1))) | P13: =IF(OR(NOT(ISNUMBER(E13)),NOT(ISNUMBER(O13))),"",IF(O13=0,E13,(E13+INDEX(Parametri!$B$10:$B$15,MATCH(MIN(Parametri!$D$10:$D$15),Parametri!$D$10:$D$15,0)))/2))
E14: =IF(D14="","",IFERROR(VLOOKUP(D14,Parametri!$A$10:$E$15,2,FALSE()),"?")) | H14: =IF(AND(ISNUMBER(B14),ISNUMBER(C14)),B14*(1+Parametri!$B$6)^C14,"") | I14: =IF(AND(ISNUMBER(B14),ISNUMBER(C14),ISNUMBER(E14),ISNUMBER(O14),ISNUMBER(P14)),MAX(0,(H14-IF(ISNUMBER(F14),F14,0)*(1+E14)^(C14-O14)*(1+P14)^O14)/(IF(E14=0,12*(C14-O14),((1+E14)^(C14-O14)-1)/((1+E14)^(1/12)-1))*(1+P14)^O14+IF(P14=0,12*O14,((1+P14)^O14-1)/((1+P14)^(1/12)-1)))),"") | J14: =IF(ISNUMBER(I14),I14/Parametri!$B$5,"") | K14: =IF(D14="","",IFERROR(VLOOKUP(D14,Parametri!$A$10:$E$15,4,FALSE()),"")) | L14: =IF(AND(ISNUMBER(F14),ISNUMBER(K14)),F14*K14,"") | M14: =IF(AND(ISNUMBER(I14),ISNUMBER(K14)),I14*K14,"") | O14: =IF(NOT(ISNUMBER(C14)),"",IF(OR(N14="permanente",NOT(ISNUMBER(K14)),K14<=MIN(Parametri!$D$10:$D$15)),0,MAX(0,MIN(Parametri!$B$7,C14)-1))) | P14: =IF(OR(NOT(ISNUMBER(E14)),NOT(ISNUMBER(O14))),"",IF(O14=0,E14,(E14+INDEX(Parametri!$B$10:$B$15,MATCH(MIN(Parametri!$D$10:$D$15),Parametri!$D$10:$D$15,0)))/2))
A16: TOTALE versamenti mensili | I16: =SUM(I5:I14) -> 1397.1203 | J16: =IF(I16="","",I16/Parametri!$B$5) -> 1.1642669 | L16: =SUM(L5:L14) -> 2000 | M16: =SUM(M5:M14) -> 449.7982

Sheet Riepilogo
A1: Pianificatore obiettivi — Riepilogo e riconciliazione
A2: Confronta i versamenti necessari con la capacità di risparmio. Tutto si aggiorna dai fogli Parametri e Obiettivi.
A4: RICONCILIAZIONE
A5: Totale versamenti mensili necessari | B5: =Obiettivi!I16 -> 1397.1203
A6: Capacità di risparmio mensile | B6: =Parametri!B5 -> 1200
A7: Margine (+) / Gap (−) mensile | B7: =B6-B5 -> -197.1203
A8: Stato del piano | B8: =IF(B7>=0,"Sostenibile","NON sostenibile") -> NON sostenibile
A9: % capacità impegnata | B9: =IFERROR(B5/B6,0) -> 1.1642669
A11: VERSAMENTI PER PRIORITÀ
A12: Versamenti 'essenziale' | B12: =SUMIF(Obiettivi!G5:G14,"essenziale",Obiettivi!I5:I14) -> 512.81144
A13: Versamenti 'importante' | B13: =SUMIF(Obiettivi!G5:G14,"importante",Obiettivi!I5:I14) -> 500.01023
A14: Versamenti 'desiderabile' | B14: =SUMIF(Obiettivi!G5:G14,"desiderabile",Obiettivi!I5:I14) -> 384.29862
A16: ALLOCAZIONE COMPLESSIVA DEL PORTAFOGLIO
A17: — Sul capitale attuale (stock) —
A18: Capitale totale attuale | B18: =SUM(Obiettivi!F5:F14) -> 5000
A19: di cui azionario | B19: =Obiettivi!L16 -> 2000
A20: di cui non azionario / liquidità | B20: =B18-B19 -> 3000
A21: QUOTA AZIONARIA complessiva | B21: =IFERROR(B19/B18,0) -> 0.4
A22: QUOTA NON AZIONARIA complessiva | B22: =IFERROR(B20/B18,0) -> 0.6
A24: — Sui nuovi versamenti (flusso mensile) —
A25: Versamento totale / mese | B25: =Obiettivi!I16 -> 1397.1203
A26: di cui in azionario / mese | B26: =Obiettivi!M16 -> 449.7982
A27: Quota azionaria del flusso | B27: =IFERROR(B26/B25,0) -> 0.32194665
A29: COME USARE L'ALLOCAZIONE COMPLESSIVA:
A30: 1. È EMERGENTE, non scelta dall'alto: deriva dai profili dei singoli obiettivi pesati per il capitale.
A31: 2. NON comprare un singolo fondo bilanciato con questa %: implementa secchiello per secchiello.
A32: Il fondo emergenza resta liquido; l'obbligazionario di un obiettivo lungo è un'altra cosa.
A33: 3. È il TARGET che alimenta it-rebalance: quella skill mantiene questa allocazione nel tempo.
A34: 4. Cambia nel tempo: il glide path (de-risking all'avvicinarsi degli obiettivi) la sposta verso il conservativo.
A35: 5. Stock ≠ flusso: l'allocazione del capitale esistente è diversa da quella dei nuovi versamenti.
A37: SE IL PIANO NON È SOSTENIBILE (Gap < 0):
A38: 1. Fondo di emergenza sempre prima (non negoziabile): è l'obiettivo 0.
A39: 2. Estinguere i debiti cari prima di investire per obiettivi discrezionali.
A40: 3. Sfruttare la sequenza: gli obiettivi a breve si completano e liberano capacità per gli altri.
A41: 4. Allungare l'orizzonte di un obiettivo non urgente (più tempo = meno versamento mensile).
... A45: Disclaimer: strumento informativo di pianificazione personale, non consulenza di investimento. I rendimenti sono ipotesi con ampia variabilità. Per scelte concrete, consultare un consulente abilitato.
